lins_healthchecks/__init__.py
lins_healthchecks/__version__.py
lins_healthchecks/api.py
lins_healthchecks/settings.py
lins_healthchecks/utils.py
lins_healthchecks-1.0.2.dist-info/LICENSE
lins_healthchecks-1.0.2.dist-info/METADATA
lins_healthchecks-1.0.2.dist-info/WHEEL
lins_healthchecks-1.0.2.dist-info/top_level.txt
lins_healthchecks-1.0.2.dist-info/RECORD
