Metadata-Version: 2.1
Name: lins-healthchecks
Version: 1.0.2
Summary: Pacote que integra containers do docker ao sistema de healthcheck da lins-ferrão
Home-page: https://bitbucket.org/grupolinsferrao/lins-health-check
Author: Grupo Lins Ferrão
Author-email: ti@grupolinsferrao.com.br
License: UNKNOWN
Platform: UNKNOWN
Classifier: Programming Language :: Python :: 3
Classifier: License :: OSI Approved :: MIT License
Classifier: Operating System :: OS Independent
Requires-Python: >=3.6
License-File: LICENSE
Requires-Dist: requests
Requires-Dist: pytz
